db_cache_manager/__init__.py
db_cache_manager/db.py
db_cache_manager-0.2.2.dist-info/LICENSE
db_cache_manager-0.2.2.dist-info/METADATA
db_cache_manager-0.2.2.dist-info/WHEEL
db_cache_manager-0.2.2.dist-info/top_level.txt
db_cache_manager-0.2.2.dist-info/RECORD
