Metadata-Version: 2.1
Name: db_cache_manager
Version: 0.2.2
Summary: Custom database connector and cache manager with default support for fingerprinting and fingerprint lookups, DAG-like chains of identical rows, and cache tables that reference each other.
Author-email: Ramtin Yazdanian <ramtin.yazdanian@epfl.ch>, Aitor Pérez <aitor.perez@epfl.ch>
Project-URL: Homepage, https://github.com/epflgraph/db-cache-manager
Project-URL: Bug Tracker, https://github.com/epflgraph/db-cache-manager/issues
Classifier: Programming Language :: Python :: 3
Classifier: License :: OSI Approved :: MIT License
Classifier: Operating System :: OS Independent
Requires-Python: >=3.7
License-File: LICENSE
Requires-Dist: pandas
Requires-Dist: pymysql
Requires-Dist: pytest
Requires-Dist: configparser
